{
	"computers" :
	[
	],
	"devices" :
	[
		{
			"name" : "MainUserHead",
			"type" : "positional",
			"driver" : "oculus",
			"src" :  "head"
		},
		{
			"name" : "LeftButton",
			"type" : "digital",
			"driver" : "mouse",
			"src" : "left"
		},
		{
			"name" : "RightButton",
			"type" : "digital",
			"driver" : "mouse",
			"src" : "right"
		},
		{
			"name" : "MiddleButton",
			"type" : "digital",
			"driver" : "keyboard",
			"src" : "f5"
		},
		{
			"name" : "KeyPageUp",
			"type" : "digital",
			"driver" : "keyboard",
			"src" : "pageup"
		},
		{
			"name" : "KeyPageDown",
			"type" : "digital",
			"driver" : "keyboard",
			"src" : "pagedown"
		}
	],
	"users" :
	[
		{
			"name" : "MainUser",
			"src" : "MainUserHead"
		}
	],
	"local" :
	{

			"host" : "dontcare",
			"window" : 
			{
				"title" : "ChangeMe",
				"x" : 0,
				"y" : 0,
				"width" : 1280,
				"height" : 720,
				"border" : false
			},
			"viewports" :
			[
                {
                    "type": "riftviewport",
                    "x": 0.0,
                    "y": 0.0,
                    "width": 1.0,
                    "height": 1,
                    "eye": "both",
                    "user": "MainUser"
                }

			]


	}
}